octoprint_wyze/__init__.py
octoprint_wyze/events.py
octoprint_wyze/wyze_devices.py
octoprint_wyze/static/css/wyze.css
octoprint_wyze/static/js/wyze.js
octoprint_wyze/static/less/wyze.less
octoprint_wyze/templates/README.txt
octoprint_wyze/templates/wyze_settings.jinja2
octoprint_wyze/templates/wyze_tab.jinja2
OctoPrint_Wyze-0.2.1.dist-info/LICENSE
OctoPrint_Wyze-0.2.1.dist-info/METADATA
OctoPrint_Wyze-0.2.1.dist-info/WHEEL
OctoPrint_Wyze-0.2.1.dist-info/entry_points.txt
OctoPrint_Wyze-0.2.1.dist-info/top_level.txt
OctoPrint_Wyze-0.2.1.dist-info/RECORD
