Metadata-Version: 2.1
Name: OctoPrint-Wyze
Version: 0.2.1
Summary: Control Wyze devices through OctoPrint
Home-page: https://github.com/eshapiro42/OctoPrint-Wyze
Author: Eric Shapiro
Author-email: eshapiro42@gmail.com
License: AGPLv3
Platform: UNKNOWN
Requires-Python: >=3.8,<4
License-File: LICENSE
Requires-Dist: OctoPrint
Requires-Dist: wyze-sdk
Requires-Dist: cryptography
